Workbook

Sheet Assumptions
A1: Financial Model - Assumptions
A3: TRAFFIC & ACQUISITION
A4: Site Traffic
A5: Total annual site visits – Year 1 | B5: 25000
A6: Annual traffic growth (YoY %) | B6: 0.2
A8: Channel Mix
A9: % of visits – paid acquisition | B9: 0.5
A10: % of visits – organic & direct | B10: 0.15
A11: % of visits – retention (email & SMS) | B11: 0.35
A12: Channel mix check (should = 100%) | B12: =SUM(B9:B11) -> 1
A14: Conversion Rates
A15: Conversion rate – paid acquisition | B15: 0.15
A16: Conversion rate – organic & direct | B16: 0.35
A17: Conversion rate – retention (email & SMS) | B17: 0.5
A19: REPEAT PURCHASES
A20: Repeat purchase rate – Year 1 | B20: 0.25
A21: Repeat purchase frequency (orders/yr) | B21: 2
A22: Annual retention improvement % | B22: 0.05
A24: ORDER ECONOMICS
A25: Average order value (gross) – Year 1 | B25: 250
A26: AOV inflation (%) | B26: 0.1
A27: Cost of goods sold (%) | B27: 0.5
A28: Annual COGS improvement % | B28: 0.01
A29: Discounts & promos (%) | B29: 0.1
A30: Return/refund rate (%) | B30: 0.1
A31: Payment processing fee (%) | B31: 0.029
A32: Marketplace/platform fee (%) | B32: 0
A34: MARKETING
A35: Paid acquisition CPC – Year 1 | B35: 5.75
A36: CPC inflation (%) | B36: 0.05
A38: FULFILMENT
A39: Shipping cost per order – Year 1 | B39: 12
A40: Shipping cost inflation (%) | B40: 0.02
A41: Handling cost per order – Year 1 | B41: 5
A42: Packaging cost per order | B42: 1.5
A43: Customer support cost per order | B43: 1.5
A45: WAREHOUSE
A46: Warehouse rent amount (when active) | B46: 150000
A47: Warehouse rent – start year | B47: 2027
A48: Warehouse rent – annual inflation (%) | B48: 0.05
A50: GENERAL & ADMINISTRATIVE
A51: Office rent amount (when active) | B51: 100000
A52: Office rent – start year | B52: 2027
A53: Office rent – annual inflation (%) | B53: 0.05
A54: Salaries, wages & benefits – Year 1 | B54: 100000
A55: Months to full team | B55: 6
A56: Professional fees – Year 1 | B56: 100000
A57: Salaries & professional fees inflation (%) | B57: 0.05
A58: Miscellaneous – Year 1 | B58: 100000
A59: Monthly SaaS / technology costs | B59: 250
A61: WORKING CAPITAL
A62: Accounts receivable days | B62: 5
A63: Inventory days – Year 1 | B63: 120
A64: Inventory turns improvement (%) | B64: 0.1
A65: Accounts payable days | B65: 30
A66: Number of days in a year | B66: 365
A67: CAPEX & DEPRECIATION
A68: Capex as % of net revenue | B68: 0.1
A69: Depreciation period (straight-line, years) | B69: 5
A71: FINANCING
A72: Initial loan amount | B72: 0
A73: Loan start year | B73: 2026
A74: Loan interest rate (%) | B74: 0.03
A75: Loan term (years) | B75: 5
A76: Initial equity injection | B76: 500000
A78: TAX
A79: Tax rate (%) | B79: 0.25

Sheet Model
E1: Startup year
E2: 2026 | F2: =+E2+1 -> 2027 | G2: =+F2+1 -> 2028 | H2: =+G2+1 -> 2029 | I2: =+H2+1 -> 2030 | J2: =+I2+1 -> 2031
A3: Balance sheet check | E3: =IFERROR(IF(ABS(E194)>1,"ERROR","OK"),"OK") -> OK | F3: =IFERROR(IF(ABS(F194)>1,"ERROR","OK"),"OK") -> OK | G3: =IFERROR(IF(ABS(G194)>1,"ERROR","OK"),"OK") -> OK | H3: =IFERROR(IF(ABS(H194)>1,"ERROR","OK"),"OK") -> OK | I3: =IFERROR(IF(ABS(I194)>1,"ERROR","OK"),"OK") -> OK | J3: =IFERROR(IF(ABS(J194)>1,"ERROR","OK"),"OK") -> OK
A5: Assumptions
A7: Acquisition Channels
A8: Site traffic
A9: Total annual site visits – Year 1 | D9: =Assumptions!B5 -> 25000
A10: Annual traffic growth (YoY %) | D10: =Assumptions!B6 -> 0.2
A12: Channel mix
A13: % of visits – paid acquisition | D13: =Assumptions!B9 -> 0.5
A14: % of visits – organic & direct | D14: =Assumptions!B10 -> 0.15
A15: % of visits – retention (email & SMS) | D15: =Assumptions!B11 -> 0.35
A16: Total traffic mix | D16: =SUM(D13:D15) -> 1
A18: Traffic by channel
A19: Paid acquisition | E19: =$D$9*$D13 -> 12500 | F19: =E19*(1+$D$10) -> 15000 | G19: =F19*(1+$D$10) -> 18000 | H19: =G19*(1+$D$10) -> 21600 | I19: =H19*(1+$D$10) -> 25920 | J19: =I19*(1+$D$10) -> 31104
A20: Organic & direct | E20: =$D$9*$D14 -> 3750 | F20: =E20*(1+$D$10) -> 4500 | G20: =F20*(1+$D$10) -> 5400 | H20: =G20*(1+$D$10) -> 6480 | I20: =H20*(1+$D$10) -> 7776 | J20: =I20*(1+$D$10) -> 9331.2
A21: Retention (email & SMS) | E21: =$D$9*$D15 -> 8750 | F21: =E21*(1+$D$10) -> 10500 | G21: =F21*(1+$D$10) -> 12600 | H21: =G21*(1+$D$10) -> 15120 | I21: =H21*(1+$D$10) -> 18144 | J21: =I21*(1+$D$10) -> 21772.8
A22: Total annual visits | E22: =D9 -> 25000 | F22: =E22*(1+$D$10) -> 30000 | G22: =F22*(1+$D$10) -> 36000 | H22: =G22*(1+$D$10) -> 43200 | I22: =H22*(1+$D$10) -> 51840 | J22: =I22*(1+$D$10) -> 62208
A24: Orders Placed
A25: Conversion rates
A26: Conversion rate – paid acquisition | D26: =Assumptions!B15 -> 0.15
A27: Conversion rate – organic & direct | D27: =Assumptions!B16 -> 0.35
A28: Conversion rate – retention (email & SMS) | D28: =Assumptions!B17 -> 0.5
A29: Repeat purchase rate – Year 1 | D29: =Assumptions!B20 -> 0.25
A30: Repeat purchase frequency (orders/yr) | D30: =Assumptions!B21 -> 2
A31: Annual retention improvement % | D31: =Assumptions!B22 -> 0.05
A33: Orders by channel
A34: Paid acquisition | E34: =E19*$D26 -> 1875 | F34: =F19*$D26 -> 2250 | G34: =G19*$D26 -> 2700 | H34: =H19*$D26 -> 3240 | I34: =I19*$D26 -> 3888 | J34: =J19*$D26 -> 4665.6
A35: Organic & direct | E35: =E20*$D27 -> 1312.5 | F35: =F20*$D27 -> 1575 | G35: =G20*$D27 -> 1890 | H35: =H20*$D27 -> 2268 | I35: =I20*$D27 -> 2721.6 | J35: =J20*$D27 -> 3265.92
A36: Retention (email & SMS) | E36: =E21*$D28 -> 4375 | F36: =F21*$D28 -> 5250 | G36: =G21*$D28 -> 6300 | H36: =H21*$D28 -> 7560 | I36: =I21*$D28 -> 9072 | J36: =J21*$D28 -> 10886.4
A37: New orders (from traffic) | E37: =SUM(E34:E36) -> 7562.5 | F37: =SUM(F34:F36) -> 9075 | G37: =SUM(G34:G36) -> 10890 | H37: =SUM(H34:H36) -> 13068 | I37: =SUM(I34:I36) -> 15681.6 | J37: =SUM(J34:J36) -> 18817.92
A38: Cumulative new customers (prior years) | E38: 0 | F38: =E37 -> 7562.5 | G38: =E37+F37 -> 16637.5 | H38: =SUM($E$37:G37) -> 27527.5 | I38: =SUM($E$37:H37) -> 40595.5 | J38: =SUM($E$37:I37) -> 56277.1
A39: Effective repeat rate | E39: =$D$29 -> 0.25 | F39: =$D$29*(1+$D$31)^1 -> 0.2625 | G39: =$D$29*(1+$D$31)^2 -> 0.275625 | H39: =$D$29*(1+$D$31)^3 -> 0.28940625 | I39: =$D$29*(1+$D$31)^4 -> 0.30387656 | J39: =$D$29*(1+$D$31)^5 -> 0.31907039
A40: Repeat orders | E40: 0 | F40: =F38*F39*$D$30 -> 3970.3125 | G40: =G38*G39*$D$30 -> 9171.4219 | H40: =H38*H39*$D$30 -> 15933.261 | I40: =I38*I39*$D$30 -> 24672.042 | J40: =J38*J39*$D$30 -> 35912.713
A41: Gross orders (new + repeat) | E41: =E37+E40 -> 7562.5 | F41: =F37+F40 -> 13045.312 | G41: =G37+G40 -> 20061.422 | H41: =H37+H40 -> 29001.261 | I41: =I37+I40 -> 40353.642 | J41: =J37+J40 -> 54730.633
A43: Order Details
A44: Average order value (gross) – Year 1 | D44: =Assumptions!B25 -> 250
A45: AOV inflation (%) | D45: =Assumptions!B26 -> 0.1
A46: Cost of goods sold (%) | D46: =Assumptions!B27 -> 0.5
A47: Annual COGS improvement % | D47: =Assumptions!B28 -> 0.01
A48: Discounts & promos (%) | D48: =Assumptions!B29 -> 0.1
A49: Return/refund rate (%) | D49: =Assumptions!B30 -> 0.1
A50: Payment processing fee (%) | D50: =Assumptions!B31 -> 0.029
A51: Marketplace/platform fee (%) | D51: =Assumptions!B32 -> 0
A53: Average order value (gross) per year | E53: =D44 -> 250 | F53: =E53*(1+$D45) -> 275 | G53: =F53*(1+$D45) -> 302.5 | H53: =G53*(1+$D45) -> 332.75 | I53: =H53*(1+$D45) -> 366.025 | J53: =I53*(1+$D45) -> 402.6275
A54: Average net order value per year | E54: =(E53*(1-$D$48)) -> 225 | F54: =(F53*(1-$D$48)) -> 247.5 | G54: =(G53*(1-$D$48)) -> 272.25 | H54: =(H53*(1-$D$48)) -> 299.475 | I54: =(I53*(1-$D$48)) -> 329.4225 | J54: =(J53*(1-$D$48)) -> 362.36475
A56: Marketing – Paid Acquisition (Variable)
A57: Paid acquisition cost per click (CPC) – Year 1 | D57: =Assumptions!B35 -> 5.75
A58: CPC inflation (%) | D58: =Assumptions!B36 -> 0.05
A60: CPC per year | E60: =D57 -> 5.75 | F60: =E60*(1+$D58) -> 6.0375 | G60: =F60*(1+$D58) -> 6.339375 | H60: =G60*(1+$D58) -> 6.6563438 | I60: =H60*(1+$D58) -> 6.9891609 | J60: =I60*(1+$D58) -> 7.338619
A62: Order Fulfilment
A63: Variable – per order
A64: Shipping cost per order – Year 1 | D64: =Assumptions!B39 -> 12
A65: Shipping cost inflation (%) | D65: =Assumptions!B40 -> 0.02
A66: Handling cost per order – Year 1 | D66: =Assumptions!B41 -> 5
A67: Packaging cost per order | D67: =Assumptions!B42 -> 1.5
A68: Customer support cost per order | D68: =Assumptions!B43 -> 1.5
A70: Shipping cost per order per year | E70: =D64 -> 12 | F70: =E70*(1+$D65) -> 12.24 | G70: =F70*(1+$D65) -> 12.4848 | H70: =G70*(1+$D65) -> 12.734496 | I70: =H70*(1+$D65) -> 12.989186 | J70: =I70*(1+$D65) -> 13.24897
A71: Handling cost per order per year | E71: =D66 -> 5 | F71: =E71*(1+$D65) -> 5.1 | G71: =F71*(1+$D65) -> 5.202 | H71: =G71*(1+$D65) -> 5.30604 | I71: =H71*(1+$D65) -> 5.4121608 | J71: =I71*(1+$D65) -> 5.520404
A72: Total variable fulfilment cost per order per year | E72: =SUM(E70:E71) -> 17 | F72: =SUM(F70:F71) -> 17.34 | G72: =SUM(G70:G71) -> 17.6868 | H72: =SUM(H70:H71) -> 18.040536 | I72: =SUM(I70:I71) -> 18.401347 | J72: =SUM(J70:J71) -> 18.769374
A74: Fixed – warehouse
A75: Warehouse rent amount (when active) | D75: =Assumptions!B46 -> 150000
A76: Warehouse rent – start year | D76: =Assumptions!B47 -> 2027
A77: Warehouse rent – annual inflation (%) | D77: =Assumptions!B48 -> 0.05
A79: Warehouse rent per year | E79: =IF(E2<$D$76,0,($D$75*(1+$D$77)^(E2-$D$84))) -> 0 | F79: =IF(F2<$D$76,0,($D$75*(1+$D$77)^(F2-$D$84))) -> 150000 | G79: =IF(G2<$D$76,0,($D$75*(1+$D$77)^(G2-$D$84))) -> 157500 | H79: =IF(H2<$D$76,0,($D$75*(1+$D$77)^(H2-$D$84))) -> 165375 | I79: =IF(I2<$D$76,0,($D$75*(1+$D$77)^(I2-$D$84))) -> 173643.75 | J79: =IF(J2<$D$76,0,($D$75*(1+$D$77)^(J2-$D$84))) -> 182325.94
A81: General & Administrative
A82: Fixed – annual run rate
A83: Office rent amount (when active) | D83: =Assumptions!B51 -> 100000
A84: Office rent – start year | D84: =Assumptions!B52 -> 2027
A85: Office rent – annual inflation (%) | D85: =Assumptions!B53 -> 0.05
A86: Salaries, wages & benefits – Year 1 | D86: =Assumptions!B54 -> 100000
A87: Months to full team | D87: =Assumptions!B55 -> 6
A88: Professional fees – Year 1 | D88: =Assumptions!B56 -> 100000
A89: Salaries & professional fees inflation (%) | D89: =Assumptions!B57 -> 0.05
A90: Miscellaneous – Year 1 | D90: =Assumptions!B58 -> 100000
A91: Monthly SaaS / technology costs | D91: =Assumptions!B59 -> 250
A93: Office rent per year | E93: =IF(E2<$D$84,0,($D$83*(1+$D$85)^(E2-$D$84))) -> 0 | F93: =IF(F2<$D$84,0,($D$83*(1+$D$85)^(F2-$D$84))) -> 100000 | G93: =IF(G2<$D$84,0,($D$83*(1+$D$85)^(G2-$D$84))) -> 105000 | H93: =IF(H2<$D$84,0,($D$83*(1+$D$85)^(H2-$D$84))) -> 110250 | I93: =IF(I2<$D$84,0,($D$83*(1+$D$85)^(I2-$D$84))) -> 115762.5 | J93: =IF(J2<$D$84,0,($D$83*(1+$D$85)^(J2-$D$84))) -> 121550.62
A94: Salaries, wages & benefits per year | E94: =$D$86*((12-$D$87)+$D$87*0.5)/12 -> 75000 | F94: =$D$86*(1+$D$89)^1 -> 105000 | G94: =$D$86*(1+$D$89)^2 -> 110250 | H94: =$D$86*(1+$D$89)^3 -> 115762.5 | I94: =$D$86*(1+$D$89)^4 -> 121550.62 | J94: =$D$86*(1+$D$89)^5 -> 127628.16
A95: Professional fees per year | E95: =D88 -> 100000 | F95: =E95*(1+$D$89) -> 105000 | G95: =F95*(1+$D$89) -> 110250 | H95: =G95*(1+$D$89) -> 115762.5 | I95: =H95*(1+$D$89) -> 121550.62 | J95: =I95*(1+$D$89) -> 127628.16
A96: Miscellaneous per year | E96: =$D$90 -> 100000 | F96: =$D$90 -> 100000 | G96: =$D$90 -> 100000 | H96: =$D$90 -> 100000 | I96: =$D$90 -> 100000 | J96: =$D$90 -> 100000
A97: SaaS / technology per year | E97: =$D$91*12 -> 3000 | F97: =E97*(1+$D$89) -> 3150 | G97: =F97*(1+$D$89) -> 3307.5 | H97: =G97*(1+$D$89) -> 3472.875 | I97: =H97*(1+$D$89) -> 3646.5188 | J97: =I97*(1+$D$89) -> 3828.8447
A98: Total G&A per year | E98: =SUM(E93:E97) -> 278000 | F98: =SUM(F93:F97) -> 413150 | G98: =SUM(G93:G97) -> 428807.5 | H98: =SUM(H93:H97) -> 445247.88 | I98: =SUM(I93:I97) -> 462510.27 | J98: =SUM(J93:J97) -> 480635.78
A100: Balance Sheet Items
A101: Current assets – working capital
A102: Accounts receivable days | D102: =Assumptions!B62 -> 5
A103: Inventory days – Year 1 | D103: =Assumptions!B63 -> 120
A104: Number of days in a year | D104: =Assumptions!B66 -> 365
A105: Inventory turns growth (YoY %) | D105: =Assumptions!B64 -> 0.1
A107: Inventory turns per year | E107: =$D$104/D103 -> 3.0416667 | F107: =E107*(1+$D$105) -> 3.3458333 | G107: =F107*(1+$D$105) -> 3.6804167 | H107: =G107*(1+$D$105) -> 4.0484583 | I107: =H107*(1+$D$105) -> 4.4533042 | J107: =I107*(1+$D$105) -> 4.8986346
A109: Current liabilities – working capital
A110: Accounts payable days | D110: =Assumptions!B65 -> 30
A112: Capex & depreciation
A113: Capex as % of net revenue | D113: =Assumptions!B68 -> 0.1
A114: Depreciation period (straight-line, years) | D114: =Assumptions!B69 -> 5
A116: Capex – assets & equipment per year | E116: =E134*$D$113 -> 189062.5 | F116: =F134*$D$113 -> 358746.09 | G116: =G134*$D$113 -> 606858.01 | H116: =H134*$D$113 -> 965016.96 | I116: =I134*$D$113 -> 1477044.2 | J116: =J134*$D$113 -> 2203605.8
A118: Financing – Debt
A119: Initial loan amount | D119: =Assumptions!B72 -> 0
A120: Loan start year | D120: =Assumptions!B73 -> 2026
A121: Loan interest rate (%) | D121: =Assumptions!B74 -> 0.03
A122: Loan term (years) | D122: =Assumptions!B75 -> 5
...

Sheet Financial Statements
A1: Financial Statements
B2: 2026 | C2: 2027 | D2: 2028 | E2: 2029 | F2: 2030 | G2: 2031
A4: Income Statement
A6: Gross revenue | B6: =Model!E134 -> 1890625 | C6: =Model!F134 -> 3587460.9 | D6: =Model!G134 -> 6068580.1 | E6: =Model!H134 -> 9650169.6 | F6: =Model!I134 -> 14770442 | G6: =Model!J134 -> 22036058
A7: Less: Discounts & promotions | B7: =Model!E135 -> -189062.5 | C7: =Model!F135 -> -358746.09 | D7: =Model!G135 -> -606858.01 | E7: =Model!H135 -> -965016.96 | F7: =Model!I135 -> -1477044.2 | G7: =Model!J135 -> -2203605.8
A8: Less: Returns & refunds | B8: =Model!E136 -> -189062.5 | C8: =Model!F136 -> -358746.09 | D8: =Model!G136 -> -606858.01 | E8: =Model!H136 -> -965016.96 | F8: =Model!I136 -> -1477044.2 | G8: =Model!J136 -> -2203605.8
A9: Less: Platform fees | B9: =Model!E137 -> 0 | C9: =Model!F137 -> 0 | D9: =Model!G137 -> 0 | E9: =Model!H137 -> 0 | F9: =Model!I137 -> 0 | G9: =Model!J137 -> 0
A10: Less: Payment processing | B10: =Model!E138 -> -54828.125 | C10: =Model!F138 -> -104036.37 | D10: =Model!G138 -> -175988.82 | E10: =Model!H138 -> -279854.92 | F10: =Model!I138 -> -428342.81 | G10: =Model!J138 -> -639045.68
A11: Net revenue | B11: =Model!E139 -> 1457671.9 | C11: =Model!F139 -> 2765932.4 | D11: =Model!G139 -> 4678875.3 | E11: =Model!H139 -> 7440280.8 | F11: =Model!I139 -> 11388011 | G11: =Model!J139 -> 16989801
A13: Cost of goods sold | B13: =Model!E142 -> 945312.5 | C13: =Model!F142 -> 1775793.2 | D13: =Model!G142 -> 2973907.7 | E13: =Model!H142 -> 4681775 | F13: =Model!I142 -> 7094213.7 | G13: =Model!J142 -> 10478036
A14: Gross profit | B14: =Model!E143 -> 512359.38 | C14: =Model!F143 -> 990139.22 | D14: =Model!G143 -> 1704967.6 | E14: =Model!H143 -> 2758505.8 | F14: =Model!I143 -> 4293796.9 | G14: =Model!J143 -> 6511764.7
A15: Gross margin % | B15: =Model!E144 -> 0.35149157 | C15: =Model!F144 -> 0.35797665 | D15: =Model!G144 -> 0.36439689 | E15: =Model!H144 -> 0.37075292 | F15: =Model!I144 -> 0.37704539 | G15: =Model!J144 -> 0.38327494
A17: Variable operating expenses
A18: Marketing (paid acquisition) | B18: =Model!E147 -> 71875 | C18: =Model!F147 -> 90562.5 | D18: =Model!G147 -> 114108.75 | E18: =Model!H147 -> 143777.03 | F18: =Model!I147 -> 181159.05 | G18: =Model!J147 -> 228260.4
A19: Shipping & handling | B19: =Model!E148 -> 128562.5 | C19: =Model!F148 -> 226205.72 | D19: =Model!G148 -> 354822.36 | E19: =Model!H148 -> 523198.29 | F19: =Model!I148 -> 742561.36 | G19: =Model!J148 -> 1027259.7
A20: Packaging | B20: =Model!E149 -> 11343.75 | C20: =Model!F149 -> 19567.969 | D20: =Model!G149 -> 30092.133 | E20: =Model!H149 -> 43501.892 | F20: =Model!I149 -> 60530.463 | G20: =Model!J149 -> 82095.949
A21: Customer support | B21: =Model!E150 -> 11343.75 | C21: =Model!F150 -> 19567.969 | D21: =Model!G150 -> 30092.133 | E21: =Model!H150 -> 43501.892 | F21: =Model!I150 -> 60530.463 | G21: =Model!J150 -> 82095.949
A22: Total variable costs | B22: =Model!E151 -> 223125 | C22: =Model!F151 -> 355904.16 | D22: =Model!G151 -> 529115.37 | E22: =Model!H151 -> 753979.1 | F22: =Model!I151 -> 1044781.3 | G22: =Model!J151 -> 1419712
A23: Contribution margin | B23: =Model!E152 -> 289234.38 | C23: =Model!F152 -> 634235.06 | D23: =Model!G152 -> 1175852.2 | E23: =Model!H152 -> 2004526.7 | F23: =Model!I152 -> 3249015.6 | G23: =Model!J152 -> 5092052.7
A24: Contribution margin % | B24: =Model!E153 -> 0.19842214 | C24: =Model!F153 -> 0.22930245 | D24: =Model!G153 -> 0.25131087 | E24: =Model!H153 -> 0.26941547 | F24: =Model!I153 -> 0.28530142 | G24: =Model!J153 -> 0.29971233
A26: Fixed operating expenses
A27: Warehouse / fulfilment | B27: =Model!E156 -> 0 | C27: =Model!F156 -> 150000 | D27: =Model!G156 -> 157500 | E27: =Model!H156 -> 165375 | F27: =Model!I156 -> 173643.75 | G27: =Model!J156 -> 182325.94
A28: General & administrative | B28: =Model!E157 -> 278000 | C28: =Model!F157 -> 413150 | D28: =Model!G157 -> 428807.5 | E28: =Model!H157 -> 445247.88 | F28: =Model!I157 -> 462510.27 | G28: =Model!J157 -> 480635.78
A29: Total fixed costs | B29: =Model!E158 -> 278000 | C29: =Model!F158 -> 563150 | D29: =Model!G158 -> 586307.5 | E29: =Model!H158 -> 610622.88 | F29: =Model!I158 -> 636154.02 | G29: =Model!J158 -> 662961.72
A31: EBITDA | B31: =Model!E159 -> 11234.375 | C31: =Model!F159 -> 71085.062 | D31: =Model!G159 -> 589544.71 | E31: =Model!H159 -> 1393903.8 | F31: =Model!I159 -> 2612861.5 | G31: =Model!J159 -> 4429091
A32: EBITDA margin % | B32: =Model!E160 -> 0.0077070671 | C32: =Model!F160 -> 0.025700217 | D32: =Model!G160 -> 0.12600137 | E32: =Model!H160 -> 0.1873456 | F32: =Model!I160 -> 0.22943968 | G32: =Model!J160 -> 0.26069117
A34: Depreciation | B34: =Model!E162 -> 37812.5 | C34: =Model!F162 -> 109561.72 | D34: =Model!G162 -> 230933.32 | E34: =Model!H162 -> 423936.71 | F34: =Model!I162 -> 719345.55 | G34: =Model!J162 -> 1267566.5
A35: Interest expense | B35: =Model!E163 -> 0 | C35: =Model!F163 -> 0 | D35: =Model!G163 -> 0 | E35: =Model!H163 -> 0 | F35: =Model!I163 -> 0 | G35: =Model!J163 -> 0
A36: Earnings before tax (EBT) | B36: =Model!E164 -> -26578.125 | C36: =Model!F164 -> -38476.656 | D36: =Model!G164 -> 358611.39 | E36: =Model!H164 -> 969967.12 | F36: =Model!I164 -> 1893516 | G36: =Model!J164 -> 3161524.5
A38: Income tax | B38: =Model!E166 -> 0 | C38: =Model!F166 -> 0 | D38: =Model!G166 -> 89652.848 | E38: =Model!H166 -> 242491.78 | F38: =Model!I166 -> 473379 | G38: =Model!J166 -> 790381.11
A39: Net income | B39: =Model!E167 -> -26578.125 | C39: =Model!F167 -> -38476.656 | D39: =Model!G167 -> 268958.54 | E39: =Model!H167 -> 727475.34 | F39: =Model!I167 -> 1420137 | G39: =Model!J167 -> 2371143.3
A42: Balance Sheet
A44: ASSETS
A45: Cash | B45: =Model!E175 -> 87452.055 | C45: =Model!F175 -> -358918.29 | D45: =Model!G175 -> -656665.38 | E45: =Model!H175 -> -697641.59 | F45: =Model!I175 -> -303685.99 | G45: =Model!J175 -> 817671.64
A46: Accounts receivable | B46: =Model!E176 -> 19968.108 | C46: =Model!F176 -> 37889.485 | D46: =Model!G176 -> 64094.182 | E46: =Model!H176 -> 101921.65 | F46: =Model!I176 -> 156000.15 | G46: =Model!J176 -> 232736.99
A47: Inventory | B47: =Model!E177 -> 310787.67 | C47: =Model!F177 -> 530747.65 | D47: =Model!G177 -> 808035.6 | E47: =Model!H177 -> 1156434 | F47: =Model!I177 -> 1593022.5 | G47: =Model!J177 -> 2138970.7
A48: Total current assets | B48: =Model!E178 -> 418207.83 | C48: =Model!F178 -> 209718.84 | D48: =Model!G178 -> 215464.4 | E48: =Model!H178 -> 560714.1 | F48: =Model!I178 -> 1445336.7 | G48: =Model!J178 -> 3189379.3
A49: Property & equipment (PP&E, net) | B49: =Model!E179 -> 151250 | C49: =Model!F179 -> 400434.38 | D49: =Model!G179 -> 776359.07 | E49: =Model!H179 -> 1317439.3 | F49: =Model!I179 -> 2075137.9 | G49: =Model!J179 -> 3011177.2
A50: Total assets | B50: =Model!E180 -> 569457.83 | C50: =Model!F180 -> 610153.22 | D50: =Model!G180 -> 991823.47 | E50: =Model!H180 -> 1878153.4 | F50: =Model!I180 -> 3520474.6 | G50: =Model!J180 -> 6200556.5
A52: LIABILITIES
A53: Accounts payable | B53: =Model!E184 -> 96035.959 | C53: =Model!F184 -> 175208 | D53: =Model!G184 -> 287919.7 | E53: =Model!H184 -> 446774.31 | F53: =Model!I184 -> 668958.5 | G53: =Model!J184 -> 977897.08
A54: Total current liabilities | B54: =Model!E185 -> 96035.959 | C54: =Model!F185 -> 175208 | D54: =Model!G185 -> 287919.7 | E54: =Model!H185 -> 446774.31 | F54: =Model!I185 -> 668958.5 | G54: =Model!J185 -> 977897.08
A55: Long-term debt | B55: =Model!E186 -> 0 | C55: =Model!F186 -> 0 | D55: =Model!G186 -> 0 | E55: =Model!H186 -> 0 | F55: =Model!I186 -> 0 | G55: =Model!J186 -> 0
A56: Total liabilities | B56: =Model!E187 -> 96035.959 | C56: =Model!F187 -> 175208 | D56: =Model!G187 -> 287919.7 | E56: =Model!H187 -> 446774.31 | F56: =Model!I187 -> 668958.5 | G56: =Model!J187 -> 977897.08
A58: SHAREHOLDERS' EQUITY
A59: Share capital | B59: =Model!E189 -> 500000 | C59: =Model!F189 -> 500000 | D59: =Model!G189 -> 500000 | E59: =Model!H189 -> 500000 | F59: =Model!I189 -> 500000 | G59: =Model!J189 -> 500000
A60: Retained earnings | B60: =Model!E190 -> -26578.125 | C60: =Model!F190 -> -65054.781 | D60: =Model!G190 -> 203903.76 | E60: =Model!H190 -> 931379.1 | F60: =Model!I190 -> 2351516.1 | G60: =Model!J190 -> 4722659.4
A61: Total equity | B61: =Model!E191 -> 473421.88 | C61: =Model!F191 -> 434945.22 | D61: =Model!G191 -> 703903.76 | E61: =Model!H191 -> 1431379.1 | F61: =Model!I191 -> 2851516.1 | G61: =Model!J191 -> 5222659.4
A63: Total liabilities & equity | B63: =Model!E192 -> 569457.83 | C63: =Model!F192 -> 610153.22 | D63: =Model!G192 -> 991823.47 | E63: =Model!H192 -> 1878153.4 | F63: =Model!I192 -> 3520474.6 | G63: =Model!J192 -> 6200556.5
A64: Balance check | B64: =Model!E194 -> 0 | C64: =Model!F194 -> 0 | D64: =Model!G194 -> 0 | E64: =Model!H194 -> 0 | F64: =Model!I194 -> 0 | G64: =Model!J194 -> 0
A67: Cash Flow Statement
A69: Operating activities
A70: Net income | B70: =Model!E199 -> -26578.125 | C70: =Model!F199 -> -38476.656 | D70: =Model!G199 -> 268958.54 | E70: =Model!H199 -> 727475.34 | F70: =Model!I199 -> 1420137 | G70: =Model!J199 -> 2371143.3
A71: Depreciation | B71: =Model!E200 -> 37812.5 | C71: =Model!F200 -> 109561.72 | D71: =Model!G200 -> 230933.32 | E71: =Model!H200 -> 423936.71 | F71: =Model!I200 -> 719345.55 | G71: =Model!J200 -> 1267566.5
A72: Changes in working capital
A73: Accounts receivable | B73: =Model!E202 -> 19968.108 | C73: =Model!F202 -> 17921.377 | D73: =Model!G202 -> 26204.697 | E73: =Model!H202 -> 37827.473 | F73: =Model!I202 -> 54078.491 | G73: =Model!J202 -> 76736.848
A74: Inventory | B74: =Model!E203 -> 310787.67 | C74: =Model!F203 -> 219959.97 | D74: =Model!G203 -> 277287.95 | E74: =Model!H203 -> 348398.43 | F74: =Model!I203 -> 436588.47 | G74: =Model!J203 -> 545948.2
A75: Accounts payable | B75: =Model!E204 -> 96035.959 | C75: =Model!F204 -> 79172.04 | D75: =Model!G204 -> 112711.7 | E75: =Model!H204 -> 158854.6 | F75: =Model!I204 -> 222184.19 | G75: =Model!J204 -> 308938.58
A76: Net cash from operations | B76: =Model!E205 -> -223485.45 | C76: =Model!F205 -> -87624.249 | D76: =Model!G205 -> 309110.92 | E76: =Model!H205 -> 924040.76 | F76: =Model!I205 -> 1870999.8 | G76: =Model!J205 -> 3324963.4
A78: Investing activities
A79: Capital expenditures (capex) | B79: =Model!E208 -> 189062.5 | C79: =Model!F208 -> 358746.09 | D79: =Model!G208 -> 606858.01 | E79: =Model!H208 -> 965016.96 | F79: =Model!I208 -> 1477044.2 | G79: =Model!J208 -> 2203605.8
A80: Net cash from investing | B80: =Model!E209 -> 189062.5 | C80: =Model!F209 -> 358746.09 | D80: =Model!G209 -> 606858.01 | E80: =Model!H209 -> 965016.96 | F80: =Model!I209 -> 1477044.2 | G80: =Model!J209 -> 2203605.8
A82: Financing activities
A83: Debt issued (new borrowings) | B83: =Model!E212 -> 0 | C83: =Model!F212 -> 0 | D83: =Model!G212 -> 0 | E83: =Model!H212 -> 0 | F83: =Model!I212 -> 0 | G83: =Model!J212 -> 0
A84: Debt repaid (principal) | B84: =Model!E213 -> 0 | C84: =Model!F213 -> 0 | D84: =Model!G213 -> 0 | E84: =Model!H213 -> 0 | F84: =Model!I213 -> 0 | G84: =Model!J213 -> 0
A85: Equity contributed | B85: =Model!E215 -> 500000 | C85: =Model!F215 -> 0 | D85: =Model!G215 -> 0 | E85: =Model!H215 -> 0 | F85: =Model!I215 -> 0 | G85: =Model!J215 -> 0
A86: Net cash from financing | B86: =Model!E218 -> 500000 | C86: =Model!F218 -> 0 | D86: =Model!G218 -> 0 | E86: =Model!H218 -> 0 | F86: =Model!I218 -> 0 | G86: =Model!J218 -> 0
A88: Opening cash balance | B88: =Model!E220 -> 0 | C88: =Model!F220 -> 87452.055 | D88: =Model!G220 -> -358918.29 | E88: =Model!H220 -> -656665.38 | F88: =Model!I220 -> -697641.59 | G88: =Model!J220 -> -303685.99
A89: Net change in cash | B89: =Model!E221 -> 87452.055 | C89: =Model!F221 -> -446370.34 | D89: =Model!G221 -> -297747.09 | E89: =Model!H221 -> -40976.204 | F89: =Model!I221 -> 393955.59 | G89: =Model!J221 -> 1121357.6
A90: Closing cash balance | B90: =Model!E222 -> 87452.055 | C90: =Model!F222 -> -358918.29 | D90: =Model!G222 -> -656665.38 | E90: =Model!H222 -> -697641.59 | F90: =Model!I222 -> -303685.99 | G90: =Model!J222 -> 817671.64

Sheet Dashboard
A1: Dashboard
B2: 2026 | C2: 2027 | D2: 2028 | E2: 2029 | F2: 2030 | G2: 2031
A4: Key Performance Indicators
A5: Profitability
A6: Net revenue | B6: =Model!E139 -> 1457671.9 | C6: =Model!F139 -> 2765932.4 | D6: =Model!G139 -> 4678875.3 | E6: =Model!H139 -> 7440280.8 | F6: =Model!I139 -> 11388011 | G6: =Model!J139 -> 16989801
A7: Revenue growth % | B7: N/A | C7: =C6/B6-1 -> 0.8975 | D7: =D6/C6-1 -> 0.6916087 | E7: =E6/D6-1 -> 0.59018575 | F7: =F6/E6-1 -> 0.53058883 | G7: =G6/F6-1 -> 0.49190241
A8: Gross profit | B8: =Model!E143 -> 512359.38 | C8: =Model!F143 -> 990139.22 | D8: =Model!G143 -> 1704967.6 | E8: =Model!H143 -> 2758505.8 | F8: =Model!I143 -> 4293796.9 | G8: =Model!J143 -> 6511764.7
A9: Gross margin % | B9: =Model!E144 -> 0.35149157 | C9: =Model!F144 -> 0.35797665 | D9: =Model!G144 -> 0.36439689 | E9: =Model!H144 -> 0.37075292 | F9: =Model!I144 -> 0.37704539 | G9: =Model!J144 -> 0.38327494
A10: EBITDA | B10: =Model!E159 -> 11234.375 | C10: =Model!F159 -> 71085.062 | D10: =Model!G159 -> 589544.71 | E10: =Model!H159 -> 1393903.8 | F10: =Model!I159 -> 2612861.5 | G10: =Model!J159 -> 4429091
A11: EBITDA margin % | B11: =Model!E160 -> 0.0077070671 | C11: =Model!F160 -> 0.025700217 | D11: =Model!G160 -> 0.12600137 | E11: =Model!H160 -> 0.1873456 | F11: =Model!I160 -> 0.22943968 | G11: =Model!J160 -> 0.26069117
A12: Net income | B12: =Model!E167 -> -26578.125 | C12: =Model!F167 -> -38476.656 | D12: =Model!G167 -> 268958.54 | E12: =Model!H167 -> 727475.34 | F12: =Model!I167 -> 1420137 | G12: =Model!J167 -> 2371143.3
A13: Unit Economics
A14: Customer acquisition cost | B14: =Model!E255 -> 38.333333 | C14: =Model!F255 -> 40.25 | D14: =Model!G255 -> 42.2625 | E14: =Model!H255 -> 44.375625 | F14: =Model!I255 -> 46.594406 | G14: =Model!J255 -> 48.924127
A15: Average order value | B15: =Model!E134/Model!E41 -> 250 | C15: =Model!F134/Model!F41 -> 275 | D15: =Model!G134/Model!G41 -> 302.5 | E15: =Model!H134/Model!H41 -> 332.75 | F15: =Model!I134/Model!I41 -> 366.025 | G15: =Model!J134/Model!J41 -> 402.6275
A16: Contribution margin / order | B16: =Model!E256 -> 47.75 | C16: =Model!F256 -> 55.56 | D16: =Model!G256 -> 64.300575 | E16: =Model!H256 -> 74.076218 | F16: =Model!I256 -> 85.002851 | G16: =Model!J256 -> 97.209056
A17: Payback (# of orders) | B17: =Model!E257 -> 0.80279232 | C17: =Model!F257 -> 0.72444204 | D17: =Model!G257 -> 0.65726473 | E17: =Model!H257 -> 0.5990536 | F17: =Model!I257 -> 0.5481511 | G17: =Model!J257 -> 0.50328775
A18: Volume
A19: Total orders | B19: =Model!E41 -> 7562.5 | C19: =Model!F41 -> 13045.312 | D19: =Model!G41 -> 20061.422 | E19: =Model!H41 -> 29001.261 | F19: =Model!I41 -> 40353.642 | G19: =Model!J41 -> 54730.633

Sheet Chart Data
B1: 2026 | C1: 2027 | D1: 2028 | E1: 2029 | F1: 2030 | G1: 2031
A2: Revenue | B2: =Model!E134 -> 1890625 | C2: =Model!F134 -> 3587460.9 | D2: =Model!G134 -> 6068580.1 | E2: =Model!H134 -> 9650169.6 | F2: =Model!I134 -> 14770442 | G2: =Model!J134 -> 22036058
A3: Net income | B3: =Model!E167 -> -26578.125 | C3: =Model!F167 -> -38476.656 | D3: =Model!G167 -> 268958.54 | E3: =Model!H167 -> 727475.34 | F3: =Model!I167 -> 1420137 | G3: =Model!J167 -> 2371143.3
B5: 2026 | C5: 2027 | D5: 2028 | E5: 2029 | F5: 2030 | G5: 2031
A6: Gross margin % | B6: =Model!E144 -> 0.35149157 | C6: =Model!F144 -> 0.35797665 | D6: =Model!G144 -> 0.36439689 | E6: =Model!H144 -> 0.37075292 | F6: =Model!I144 -> 0.37704539 | G6: =Model!J144 -> 0.38327494
A7: EBITDA margin % | B7: =Model!E160 -> 0.0077070671 | C7: =Model!F160 -> 0.025700217 | D7: =Model!G160 -> 0.12600137 | E7: =Model!H160 -> 0.1873456 | F7: =Model!I160 -> 0.22943968 | G7: =Model!J160 -> 0.26069117
A8: Contribution margin % | B8: =Model!E153 -> 0.19842214 | C8: =Model!F153 -> 0.22930245 | D8: =Model!G153 -> 0.25131087 | E8: =Model!H153 -> 0.26941547 | F8: =Model!I153 -> 0.28530142 | G8: =Model!J153 -> 0.29971233
B10: 2026 | C10: 2027 | D10: 2028 | E10: 2029 | F10: 2030 | G10: 2031
A11: CAC | B11: =Model!E255 -> 38.333333 | C11: =Model!F255 -> 40.25 | D11: =Model!G255 -> 42.2625 | E11: =Model!H255 -> 44.375625 | F11: =Model!I255 -> 46.594406 | G11: =Model!J255 -> 48.924127
A12: AOV | B12: =Model!E134/Model!E41 -> 250 | C12: =Model!F134/Model!F41 -> 275 | D12: =Model!G134/Model!G41 -> 302.5 | E12: =Model!H134/Model!H41 -> 332.75 | F12: =Model!I134/Model!I41 -> 366.025 | G12: =Model!J134/Model!J41 -> 402.6275
A13: Contribution margin / order | B13: =Model!E256 -> 47.75 | C13: =Model!F256 -> 55.56 | D13: =Model!G256 -> 64.300575 | E13: =Model!H256 -> 74.076218 | F13: =Model!I256 -> 85.002851 | G13: =Model!J256 -> 97.209056
B15: 2026 | C15: 2027 | D15: 2028 | E15: 2029 | F15: 2030 | G15: 2031
A16: Burn rate | B16: =Model!E258 -> -412547.95 | C16: =Model!F258 -> -446370.34 | D16: =Model!G258 -> -297747.09 | E16: =Model!H258 -> -40976.204 | F16: =Model!I258 -> 393955.59 | G16: =Model!J258 -> 1121357.6
A17: Cash balance | B17: =Model!E222 -> 87452.055 | C17: =Model!F222 -> -358918.29 | D17: =Model!G222 -> -656665.38 | E17: =Model!H222 -> -697641.59 | F17: =Model!I222 -> -303685.99 | G17: =Model!J222 -> 817671.64
